utilsme/__init__.py
utilsme/compression.py
utilsme/configs.py
utilsme/generate_data.py
utilsme/handle_file.py
utilsme/model_format.py
utilsme/model_validator.py
utilsme/random_value.py
utilsme/time.py
utils_me-0.1.3.17.dist-info/METADATA
utils_me-0.1.3.17.dist-info/WHEEL
utils_me-0.1.3.17.dist-info/top_level.txt
utils_me-0.1.3.17.dist-info/RECORD
