Metadata-Version: 2.1
Name: utils-me
Version: 0.1.3.17
Summary: This a sort description
Home-page: https://github.com/SiguiNag/UtilsMe.git
Author: Siguifowa Yeo
Author-email: siguifowa.yeo@gmail.com
Classifier: Programming Language :: Python :: 3.7
Classifier: Programming Language :: Python :: 3.9
Classifier: Programming Language :: Python :: 3.11
Classifier: Programming Language :: Python :: 3.12
Requires-Python: >=3.7
Requires-Dist: pandas
Requires-Dist: requests
Requires-Dist: pydantic
Requires-Dist: pyyaml
